docs/index.rst
docs/requirements.txt
docs/conf.py
docs/make.bat
docs/images/Bladed_control_screen.png
docs/images/ROSCOFramework.svg
docs/images/mhk/09_cp_wg_Ta_contour_annotated.png
docs/images/mhk/03_cp_wg_sched.png
docs/images/mhk/19_ext_wg_thrust_contour.png
docs/images/mhk/05_cp_wg_tg_sched.png
docs/images/mhk/02_cp_surface_annotated.png
docs/images/mhk/07_cp_Agen_sched_annotated.png
docs/images/mhk/12_ext_wg_tg_sched.png
docs/images/mhk/25_turb_intensity.png
docs/images/mhk/18_ext_Agen_sched.png
docs/images/mhk/26_case1_P_wg_tg_turb.png
docs/images/mhk/24_case3_P_wg_tg_ss.png
docs/images/mhk/11_ext_P.png
docs/images/mhk/16_ext_wg_sched_annotated.png
docs/images/mhk/14_fbp_flow_chart.png
docs/images/mhk/15_ext_wg_sched.png
docs/images/mhk/22_case1_P_wg_tg_ss.png
docs/images/mhk/13_ext_wg_tg_P_contour.png
docs/images/mhk/23_case2_P_wg_tg_ss.png
docs/images/mhk/21_cases_P_wg_tg_sched.png
docs/images/mhk/17_ext_tg_sched.png
docs/images/mhk/06_cp_Agen_sched.png
docs/images/mhk/04_cp_tg_sched.png
docs/images/mhk/27_case2_P_wg_tg_turb.png
docs/images/mhk/01_cp_surface.png
docs/images/mhk/20_ext_wg_thrust_sched.png
docs/images/mhk/10_cp_kp_ki_sched.png
docs/images/mhk/28_case3_P_wg_tg_turb.png
docs/images/mhk/08_cp_wg_Ta_contour.png
docs/images/examples/12_ipc_FAST_Out.png
docs/images/examples/30_shutdown_time_demo.png
docs/images/examples/01_NREL5MW_Cp.png
docs/images/examples/29_PRC_Methods.png
docs/images/examples/31_fixed_pitch_mhk_sched.png
docs/images/examples/18_pitch_offsets.png
docs/images/examples/29_Soft_Cutout.png
docs/images/examples/30_shutdown_gen_demo.png
docs/images/examples/04_NREL5MW_SimpSim.png
docs/images/examples/32_startup.png
docs/images/examples/31_fixed_pitch_mhk_sim.png
docs/images/examples/18_pitch_stuck.png
docs/images/examples/29_StartUp.png
docs/images/examples/06_MinPitch.png
docs/images/examples/03_GainSched.png
docs/images/examples/30_shutdown_yaw_demo.png
rosco-2.10.2.dist-info/RECORD
rosco-2.10.2.dist-info/WHEEL
rosco-2.10.2.dist-info/top_level.txt
rosco-2.10.2.dist-info/METADATA
rosco-2.10.2.dist-info/licenses/LICENSE
