Metadata-Version: 2.4
Name: rosco
Version: 2.10.2
Summary: A reference open source controller toolset for wind turbine applications.
Author-email: "National Wind Technology Center, NREL" <daniel.zalkind@nrel.gov>
Maintainer-email: Daniel Zalkind <daniel.zalkind@nrel.gov>
License: Apache-2.0
Project-URL: Homepage, https://github.com/NREL/ROSCO
Project-URL: Documentation, https://rosco.readthedocs.io
Keywords: wind,turbine,control,,
Classifier: Development Status :: 4 - Beta
Classifier: Intended Audience :: Science/Research
Classifier: Topic :: Scientific/Engineering
Classifier: License :: OSI Approved :: Apache Software License
Classifier: Programming Language :: Python :: 3
Classifier: Programming Language :: Python :: 3.9
Classifier: Programming Language :: Python :: 3.10
Classifier: Programming Language :: Python :: 3.11
Classifier: Programming Language :: Python :: 3.12
Classifier: Programming Language :: Python :: 3.13
Classifier: Programming Language :: Python :: 3 :: Only
Classifier: Programming Language :: Fortran
Requires-Python: >=3.9
License-File: LICENSE
Requires-Dist: control
Requires-Dist: numpy
Requires-Dist: matplotlib
Requires-Dist: scipy
Requires-Dist: pandas
Requires-Dist: pyparsing
Requires-Dist: pyYAML
Requires-Dist: pyzmq
Requires-Dist: wisdem
Requires-Dist: ruamel.yaml
Requires-Dist: openfast_io
Provides-Extra: dev
Requires-Dist: cmake; extra == "dev"
Provides-Extra: test
Requires-Dist: pytest; extra == "test"
Requires-Dist: treon; extra == "test"
Dynamic: license-file
